bareimport/__init__.py
bareimport-0.2.dist-info/LICENSE
bareimport-0.2.dist-info/METADATA
bareimport-0.2.dist-info/WHEEL
bareimport-0.2.dist-info/top_level.txt
bareimport-0.2.dist-info/RECORD
