Metadata-Version: 2.1
Name: bareimport
Version: 0.2
Summary: Import a python module even if it is in a file that does not end in '.py'
Author-email: Sean Reifschneider <jafo00@gmail.com>
Project-URL: Homepage, https://github.com/linsomniac/bareimport
Project-URL: Bug Tracker, https://github.com/linsomniac/bareimport/issues
Classifier: Programming Language :: Python :: 3
Classifier: License :: CC0 1.0 Universal (CC0 1.0) Public Domain Dedication
Classifier: Operating System :: OS Independent
Requires-Python: >=3.7
License-File: LICENSE
